gwnrtools/.version
gwnrtools/__init__.py
gwnrtools/analysis/__init__.py
gwnrtools/analysis/filter.py
gwnrtools/analysis/gw_transient_catalog.py
gwnrtools/analysis/psd.py
gwnrtools/analysis/utils.py
gwnrtools/cosmo/__init__.py
gwnrtools/cosmo/utils.py
gwnrtools/data/__init__.py
gwnrtools/data/data.py
gwnrtools/data/gw_noise_curves/advirgo.txt
gwnrtools/data/gw_noise_curves/advirgo_sqz.txt
gwnrtools/data/gw_noise_curves/advirgo_wb.txt
gwnrtools/data/gw_noise_curves/aligo.txt
gwnrtools/data/gw_noise_curves/aligo_design.txt
gwnrtools/data/gw_noise_curves/aplus.txt
gwnrtools/data/gw_noise_curves/aplus_sqzonly.txt
gwnrtools/data/gw_noise_curves/ce1.txt
gwnrtools/data/gw_noise_curves/ce2.txt
gwnrtools/data/gw_noise_curves/cosmic_explorer.txt
gwnrtools/data/gw_noise_curves/er8.txt
gwnrtools/data/gw_noise_curves/et_d.txt
gwnrtools/data/gw_noise_curves/kagra.txt
gwnrtools/data/gw_noise_curves/kagra_sqz.txt
gwnrtools/data/gw_noise_curves/kagra_wb.txt
gwnrtools/data/gw_noise_curves/o1.txt
gwnrtools/data/gw_noise_curves/o2.txt
gwnrtools/data/gw_noise_curves/o2_crossspec.txt
gwnrtools/data/gw_noise_curves/o3_h1.txt
gwnrtools/data/gw_noise_curves/o3_l1.txt
gwnrtools/data/gw_noise_curves/o3_v1.txt
gwnrtools/data/gw_noise_curves/s6.txt
gwnrtools/data/gw_noise_curves/voyager.txt
gwnrtools/graph/__init__.py
gwnrtools/graph/analysis_products.py
gwnrtools/graph/cbc.py
gwnrtools/graph/corner.py
gwnrtools/graph/misc.py
gwnrtools/graph/paraview.py
gwnrtools/graph/visualization.py
gwnrtools/nr/__init__.py
gwnrtools/nr/nr_waveform_sxs.py
gwnrtools/nr/utils.py
gwnrtools/nr/analysis/UseNRinDA_V1_08162018.py
gwnrtools/nr/analysis/__init__.py
gwnrtools/nr/analysis/filter.py
gwnrtools/nr/analysis/support.py
gwnrtools/nr/analysis/types.py
gwnrtools/nr/spec/__init__.py
gwnrtools/nr/spec/utils.py
gwnrtools/nr/spectre/__init__.py
gwnrtools/nr/spectre/evolutions/__init__.py
gwnrtools/nr/spectre/evolutions/configurations.py
gwnrtools/nr/spectre/evolutions/evolutions.py
gwnrtools-2021.9.20.dist-info/LICENSE
gwnrtools-2021.9.20.dist-info/METADATA
gwnrtools-2021.9.20.dist-info/WHEEL
gwnrtools-2021.9.20.dist-info/top_level.txt
gwnrtools-2021.9.20.dist-info/RECORD
